adopt_a_doodle-0.0.3.dist-info/METADATA
adopt_a_doodle-0.0.3.dist-info/WHEEL
adopt_a_doodle-0.0.3.dist-info/license_files/LICENSE
adopt_a_doodle/adopt.py
adopt_a_doodle/__init__.py
adopt_a_doodle/adopt_a_doodle.cpython-312-darwin.so
adopt_a_doodle-0.0.3.dist-info/RECORD
