Metadata-Version: 2.3
Name: adopt_a_doodle
Version: 0.0.3
Classifier: Programming Language :: Python :: 3
Classifier: License :: OSI Approved :: MIT License
Classifier: Operating System :: OS Independent
Requires-Dist: panda3d ~=1.10.11
License-File: LICENSE
Summary: A Python package to make the creation of Doodle actors easier!
Author-email: Vhou-Atroph <vhouatroph@proton.me>
Requires-Python: >=3.11
Project-URL: Homepage, https://github.com/Vhou-Atroph/adopt-a-doodle
Project-URL: Bug Tracker, https://github.com/Vhou-Atroph/adopt-a-doodle/issues
